Metadata-Version: 2.1
Name: rainel
Version: 1.1
Summary: Gaussian and Binomial distributions
Author: Felipe Rainel
Author-email: raineldias88@gmail.com
